chaoschain_sdk/__init__.py
chaoschain_sdk/a2a_x402_extension.py
chaoschain_sdk/chaos_agent.py
chaoschain_sdk/core_sdk.py
chaoschain_sdk/dkg.py
chaoschain_sdk/exceptions.py
chaoschain_sdk/gateway_client.py
chaoschain_sdk/google_ap2_integration.py
chaoschain_sdk/mandate_manager.py
chaoschain_sdk/payment_manager.py
chaoschain_sdk/process_integrity.py
chaoschain_sdk/py.typed
chaoschain_sdk/storage_backends.py
chaoschain_sdk/studio_manager.py
chaoschain_sdk/types.py
chaoschain_sdk/verifier_agent.py
chaoschain_sdk/wallet_manager.py
chaoschain_sdk/x402_payment_manager.py
chaoschain_sdk/x402_server.py
chaoschain_sdk/xmtp_client.py
chaoschain_sdk/proto/__init__.py
chaoschain_sdk/proto/zerog_bridge_pb2.py
chaoschain_sdk/proto/zerog_bridge_pb2_grpc.py
chaoschain_sdk/proto/zerog_inference_pb2.py
chaoschain_sdk/proto/zerog_inference_pb2_grpc.py
chaoschain_sdk/providers/__init__.py
chaoschain_sdk/providers/compute/__init__.py
chaoschain_sdk/providers/compute/base.py
chaoschain_sdk/providers/compute/zerog_compute.py
chaoschain_sdk/providers/storage/__init__.py
chaoschain_sdk/providers/storage/ario.py
chaoschain_sdk/providers/storage/base.py
chaoschain_sdk/providers/storage/ipfs_local.py
chaoschain_sdk/providers/storage/ipfs_pinata.py
chaoschain_sdk/providers/storage/irys.py
chaoschain_sdk/providers/storage/zerog_grpc.py
chaoschain_sdk/providers/storage/zerog_storage.py
chaoschain_sdk/providers/tee/__init__.py
chaoschain_sdk/providers/tee/base.py
chaoschain_sdk-0.4.0.dist-info/METADATA
chaoschain_sdk-0.4.0.dist-info/WHEEL
chaoschain_sdk-0.4.0.dist-info/top_level.txt
chaoschain_sdk-0.4.0.dist-info/RECORD
