Metadata-Version: 2.4
Name: chaoschain-sdk
Version: 0.4.0
Summary: Production SDK for building verifiable AI agents with ChaosChain Protocol - Studios, Proof of Agency, ERC-8004 (Jan 2026), x402
Author-email: ChaosChain <sumeet@chaoscha.in>
Maintainer-email: ChaosChain <sumeet@chaoscha.in>
License-Expression: MIT
Project-URL: Homepage, https://chaoschain.io
Project-URL: Documentation, https://docs.chaoschain.io
Project-URL: Repository, https://github.com/ChaosChain/chaoschain
Project-URL: Issues, https://github.com/ChaosChain/chaoschain/issues
Keywords: ai-agents,blockchain,erc-8004,x402,web3,autonomous-agents,chaoschain,crypto-payments,agent-commerce
Classifier: Development Status :: 4 - Beta
Classifier: Intended Audience :: Developers
Classifier: Operating System :: OS Independent
Classifier: Programming Language :: Python :: 3
Classifier: Programming Language :: Python :: 3.9
Classifier: Programming Language :: Python :: 3.10
Classifier: Programming Language :: Python :: 3.11
Classifier: Programming Language :: Python :: 3.12
Classifier: Topic :: Software Development :: Libraries :: Python Modules
Classifier: Topic :: Internet :: WWW/HTTP
Classifier: Topic :: Security :: Cryptography
Requires-Python: >=3.9
Requires-Dist: web3>=6.0.0
Requires-Dist: eth-account>=0.8.0
Requires-Dist: mandates-core>=0.1.3
Requires-Dist: x402>=2.0.0
Requires-Dist: cryptography>=41.0.0
Requires-Dist: pyjwt>=2.8.0
Requires-Dist: requests>=2.28.0
Requires-Dist: python-dotenv>=1.0.0
Requires-Dist: rich>=13.0.0
Provides-Extra: pinata
Requires-Dist: httpx>=0.24.0; extra == "pinata"
Provides-Extra: irys
Requires-Dist: httpx>=0.24.0; extra == "irys"
Provides-Extra: ipfs
Requires-Dist: ipfshttpclient>=0.8.0; extra == "ipfs"
Provides-Extra: 0g-storage
Provides-Extra: ario
Requires-Dist: turbo-sdk>=0.0.3; extra == "ario"
Provides-Extra: 0g-compute
Provides-Extra: phala-tee
Requires-Dist: dstack-sdk>=0.1.0; extra == "phala-tee"
Provides-Extra: morpheus
Provides-Extra: chainlink
Provides-Extra: ap2
Provides-Extra: payments-fiat
Requires-Dist: stripe>=7.0.0; extra == "payments-fiat"
Requires-Dist: paypalrestsdk>=1.13.0; extra == "payments-fiat"
Provides-Extra: 0g
Requires-Dist: chaoschain-sdk[0g-compute,0g-storage]; extra == "0g"
Provides-Extra: storage-all
Requires-Dist: chaoschain-sdk[0g-storage,ario,ipfs,irys,pinata]; extra == "storage-all"
Provides-Extra: compute-all
Requires-Dist: chaoschain-sdk[0g-compute,chainlink,morpheus]; extra == "compute-all"
Provides-Extra: all
Requires-Dist: chaoschain-sdk[0g,ario,chainlink,ipfs,irys,morpheus,payments-fiat,phala-tee,pinata]; extra == "all"
Provides-Extra: dev
Requires-Dist: pytest>=7.0.0; extra == "dev"
Requires-Dist: pytest-asyncio>=0.21.0; extra == "dev"
Requires-Dist: black>=23.0.0; extra == "dev"
Requires-Dist: isort>=5.12.0; extra == "dev"
Requires-Dist: mypy>=1.0.0; extra == "dev"
Requires-Dist: pre-commit>=3.0.0; extra == "dev"
Requires-Dist: ruff>=0.1.0; extra == "dev"
Provides-Extra: docs
Requires-Dist: sphinx>=6.0.0; extra == "docs"
Requires-Dist: sphinx-rtd-theme>=1.2.0; extra == "docs"
